whatsopt/__init__.py
whatsopt/convert_utils.py
whatsopt/logging.py
whatsopt/mooptimization.py
whatsopt/optimization.py
whatsopt/publish_utils.py
whatsopt/push_command.py
whatsopt/push_utils.py
whatsopt/show_utils.py
whatsopt/upload_utils.py
whatsopt/utils.py
whatsopt/whatsopt_client.py
whatsopt/wop.py
wop-2.5.4.dist-info/LICENSE
wop-2.5.4.dist-info/METADATA
wop-2.5.4.dist-info/WHEEL
wop-2.5.4.dist-info/entry_points.txt
wop-2.5.4.dist-info/top_level.txt
wop-2.5.4.dist-info/RECORD
