Metadata-Version: 2.1
Name: wop
Version: 2.5.4
Summary: WhatsOpt Command Line Interface
Author-email: Rémi Lafage <remi.lafage@onera.fr>
License: Apache License 2.0
Project-URL: homepage, https://github.com/whatsopt
Project-URL: repository, https://github.com/whatsopt/WhatsOpt-CLI
Project-URL: documentation, https://github.com/whatsopt/WhatsOpt-Doc#whatsopt-documentation
Keywords: WhatsOpt,command
Classifier: Development Status :: 5 - Production/Stable
Classifier: Intended Audience :: Science/Research
Classifier: Intended Audience :: Developers
Classifier: License :: OSI Approved :: Apache Software License
Classifier: Programming Language :: Python :: 3
Classifier: Topic :: Software Development
Classifier: Topic :: Scientific/Engineering
Classifier: Operating System :: Microsoft :: Windows
Classifier: Operating System :: Unix
Classifier: Operating System :: MacOS
Requires-Python: >=3.7
License-File: LICENSE
Requires-Dist: build
Requires-Dist: click >=6.7
Requires-Dist: openmdao >=3.4.0
Requires-Dist: openmdao-extensions >=1.2.0
Requires-Dist: packaging
Requires-Dist: pkginfo
Requires-Dist: requests
Requires-Dist: tabulate >=0.8.2
Requires-Dist: tomli
Requires-Dist: tomli-w
Requires-Dist: xdsmjs >=1.0.0
Provides-Extra: test
Requires-Dist: pytest ; extra == 'test'
